{
  "clinics": [
    {
      "id": 1,
      "name": "City Medical Center",
      "location": "123 Main Street, Cityville"
    },
    {
      "id": 2,
      "name": "Suburb Health Clinic",
      "location": "456 Oak Avenue, Suburbia"
    },
    {
      "id": 3,
      "name": "Downtown Wellness Center",
      "location": "789 Broadway, Downtown"
    },
    {
      "id": 4,
      "name": "Rural Family Clinic",
      "location": "101 Pine Lane, Countryside"
    },
    {
      "id": 5,
      "name": "Coastal Medical Hub",
      "location": "555 Ocean Drive, Coastal Town"
    },
    {
      "id": 6,
      "name": "Mountain View Health Center",
      "location": "777 Summit Road, Mountain City"
    }
  ],
  "specialties": [
    {
      "id": 1,
      "name": "General Medicine"
    },
    {
      "id": 2,
      "name": "Dermatology"
    },
    {
      "id": 3,
      "name": "Pediatrics"
    },
    {
      "id": 4,
      "name": "Orthopedics"
    },
    {
      "id": 5,
      "name": "Cardiology"
    },
    {
      "id": 6,
      "name": "Gynecology"
    }
  ],
  "doctors": [
    {
      "id": 1,
      "name": "Dr. Smith",
      "clinicId": 1,
      "specialtyId": 1,
      "availability": {
        "Monday": [
          {
            "10:00": true
          },
          {
            "10:20": false
          },
          {
            "10:40": true
          },
          {
            "11:00": true
          }
        ],
        "Wednesday": [
          {
            "10:00": true
          },
          {
            "10:20": false
          },
          {
            "10:40": true
          },
          {
            "11:00": true
          }
        ],
        "Friday": [
          {
            "10:20": false
          },
          {
            "10:40": true
          },
          {
            "11:00": true
          },
          {
            "11:20": true
          }
        ]
      },
      "rate": 1500,
      "img": "1.jpg"
    },
    {
      "id": 2,
      "name": "Dr. Johnson",
      "clinicId": 1,
      "specialtyId": 2,
      "availability": {
        "Monday": [
          {
            "10:20": false
          },
          {
            "10:40": true
          },
          {
            "11:00": true
          },
          {
            "11:20": true
          }
        ],
        "Tuesday": [
          {
            "10:20": false
          },
          {
            "10:40": true
          },
          {
            "11:00": true
          },
          {
            "11:20": true
          }
        ],
        "Friday": [
          {
            "10:20": false
          },
          {
            "10:40": true
          },
          {
            "11:00": true
          },
          {
            "11:20": true
          }
        ]
      },
      "rate": 3500,
      "img": "2.jpg"
    },
    {
      "id": 3,
      "name": "Dr. Williams",
      "clinicId": 2,
      "specialtyId": 3,
      "availability": {
        "Monday": [
          {
            "10:20": false
          },
          {
            "10:40": true
          },
          {
            "11:00": true
          },
          {
            "11:20": true
          }
        ],
        "Wednesday": [
          {
            "10:00": true
          },
          {
            "10:20": false
          },
          {
            "10:40": true
          },
          {
            "11:00": true
          }
        ],
        "Friday": [
          {
            "10:00": true
          },
          {
            "10:20": false
          },
          {
            "10:40": true
          },
          {
            "11:00": true
          }
        ]
      },
      "rate": 2350,
      "img": "3.jpg"
    },
    {
      "id": 4,
      "name": "Dr. Brown",
      "clinicId": 3,
      "specialtyId": 4,
      "availability": {
        "Monday": [
          {
            "10:00": true
          },
          {
            "10:20": false
          },
          {
            "10:40": true
          },
          {
            "11:00": true
          }
        ],
        "Thursday": [
          {
            "10:20": false
          },
          {
            "10:40": true
          },
          {
            "11:00": true
          },
          {
            "11:20": true
          }
        ],
        "Friday": [
          {
            "10:20": false
          },
          {
            "10:40": true
          },
          {
            "11:00": true
          },
          {
            "11:20": true
          }
        ]
      },
      "rate": 500,
      "img": "4.jpg"
    },
    {
      "id": 5,
      "name": "Dr. Davis",
      "clinicId": 4,
      "specialtyId": 5,
      "availability": {
        "Sunday": [
          {
            "10:20": false
          },
          {
            "10:40": true
          },
          {
            "11:00": true
          },
          {
            "11:20": true
          }
        ],
        "Wednesday": [
          {
            "10:20": false
          },
          {
            "10:40": true
          },
          {
            "11:00": true
          },
          {
            "11:20": true
          }
        ],
        "Saturday": [
          {
            "10:20": false
          },
          {
            "10:40": true
          },
          {
            "11:00": true
          },
          {
            "11:20": true
          }
        ]
      },
      "rate": 1200,
      "img": "5.jpg"
    },
    {
      "id": 6,
      "name": "Dr. Miller",
      "clinicId": 5,
      "specialtyId": 6,
      "availability": {
        "Monday": [
          {
            "10:20": false
          },
          {
            "10:40": true
          },
          {
            "11:00": true
          },
          {
            "11:20": true
          }
        ],
        "Wednesday": [
          {
            "10:20": false
          },
          {
            "10:40": true
          },
          {
            "11:00": true
          },
          {
            "11:20": true
          }
        ],
        "Friday": [
          {
            "10:20": false
          },
          {
            "10:40": true
          },
          {
            "11:00": true
          },
          {
            "11:20": true
          }
        ]
      },
      "rate": 5500,
      "img": "6.jpg"
    }
  ],
  "appointments": [
    {
      "id": 1,
      "doctorId": 1,
      "patientName": "John Doe",
      "time": "10:00:00",
      "day": "Saturday",
      "status": false,
      "patientId": 1
    },
    {
      "id": 2,
      "doctorId": 2,
      "patientName": "Jane Smith",
      "time": "10:00:00",
      "day": "Saturday",
      "status": false,
      "patientId": 2
    },
    {
      "id": 3,
      "doctorId": 3,
      "patientName": "Alice Johnson",
      "time": "10:00:00",
      "day": "Saturday",
      "status": false,
      "patientId": 3
    },
    {
      "time": "11:00",
      "day": "Monday",
      "doctorId": "3",
      "patientName": "moumita",
      "status": false,
      "patientId": 2,
      "id": 4
    },
    {
      "time": "11:20",
      "day": "Friday",
      "doctorId": "6",
      "patientName": "anindita",
      "status": false,
      "patientId": 4,
      "id": 5
    }
  ],
  "users": [
    {
      "id": 1,
      "name": "Rick Ray",
      "email": "rick@mail.com",
      "password": "rick123"
    },
    {
      "name": "moumita",
      "email": "moumita@mail.com",
      "password": "mou",
      "id": 2
    },
    {
      "name": "reka",
      "email": "reka@mail.com",
      "password": "mou",
      "id": 3
    },
    {
      "name": "anindita",
      "email": "ani@mail.com",
      "password": "ani1",
      "id": 4
    }
  ]
}